[
  {
    "id": 1,
    "isVaild": 1,
    "ItemName": "金币",
    "ItemIcon": "",
    "ItemQuality": 0,
    "ItemType": 0,
    "ItemDes": "",
    "BagSlotType": 0,
    "AutoUse": false,
    "BatchUseable": false,
    "UseScript": 0,
    "UseArgs": [],
    "AwakeScript": []
  },
  {
    "id": 2,
    "isVaild": 1,
    "ItemName": "木材",
    "ItemIcon": "",
    "ItemQuality": 0,
    "ItemType": 0,
    "ItemDes": "",
    "BagSlotType": 0,
    "AutoUse": false,
    "BatchUseable": false,
    "UseScript": 0,
    "UseArgs": [],
    "AwakeScript": []
  },
  {
    "id": 100,
    "isVaild": 0,
    "ItemName": "",
    "ItemIcon": "",
    "ItemQuality": 0,
    "ItemType": 0,
    "ItemDes": "",
    "BagSlotType": 0,
    "AutoUse": false,
    "BatchUseable": false,
    "UseScript": 0,
    "UseArgs": [],
    "AwakeScript": []
  },
  {
    "id": 1000,
    "isVaild": 0,
    "ItemName": "",
    "ItemIcon": "",
    "ItemQuality": 0,
    "ItemType": 0,
    "ItemDes": "",
    "BagSlotType": 0,
    "AutoUse": false,
    "BatchUseable": false,
    "UseScript": 0,
    "UseArgs": [],
    "AwakeScript": []
  },
  {
    "id": 10001,
    "isVaild": 0,
    "ItemName": "测试宝箱",
    "ItemIcon": "",
    "ItemQuality": 0,
    "ItemType": 0,
    "ItemDes": "",
    "BagSlotType": 0,
    "AutoUse": false,
    "BatchUseable": false,
    "UseScript": 1,
    "UseArgs": [
      5001001,
      22
    ],
    "AwakeScript": []
  },
  {
    "id": 10002,
    "isVaild": 0,
    "ItemName": "宝箱",
    "ItemIcon": "",
    "ItemQuality": 0,
    "ItemType": 0,
    "ItemDes": "",
    "BagSlotType": 0,
    "AutoUse": false,
    "BatchUseable": false,
    "UseScript": 1,
    "UseArgs": [],
    "AwakeScript": []
  },
  {
    "id": 10003,
    "isVaild": 0,
    "ItemName": "宝箱",
    "ItemIcon": "",
    "ItemQuality": 0,
    "ItemType": 0,
    "ItemDes": "",
    "BagSlotType": 0,
    "AutoUse": false,
    "BatchUseable": false,
    "UseScript": 1,
    "UseArgs": [],
    "AwakeScript": []
  },
  {
    "id": 10004,
    "isVaild": 0,
    "ItemName": "史莱姆装备1",
    "ItemIcon": "",
    "ItemQuality": 0,
    "ItemType": 0,
    "ItemDes": "",
    "BagSlotType": 0,
    "AutoUse": false,
    "BatchUseable": false,
    "UseScript": 2,
    "UseArgs": [],
    "AwakeScript": [
      {
        "ScriptName": 3,
        "ScriptValue": []
      }
    ]
  },
  {
    "id": 10005,
    "isVaild": 0,
    "ItemName": "",
    "ItemIcon": "",
    "ItemQuality": 0,
    "ItemType": 0,
    "ItemDes": "",
    "BagSlotType": 0,
    "AutoUse": false,
    "BatchUseable": false,
    "UseScript": 0,
    "UseArgs": [],
    "AwakeScript": []
  },
  {
    "id": 10006,
    "isVaild": 0,
    "ItemName": "英雄经验",
    "ItemIcon": "",
    "ItemQuality": 0,
    "ItemType": 0,
    "ItemDes": "",
    "BagSlotType": 0,
    "AutoUse": false,
    "BatchUseable": false,
    "UseScript": 0,
    "UseArgs": [],
    "AwakeScript": [
      {
        "ScriptName": 1,
        "ScriptValue": [
          10001,
          100
        ]
      }
    ]
  },
  {
    "id": 10007,
    "isVaild": 0,
    "ItemName": "",
    "ItemIcon": "",
    "ItemQuality": 0,
    "ItemType": 0,
    "ItemDes": "",
    "BagSlotType": 1,
    "AutoUse": false,
    "BatchUseable": false,
    "UseScript": 0,
    "UseArgs": [],
    "AwakeScript": []
  },
  {
    "id": 10008,
    "isVaild": 0,
    "ItemName": "",
    "ItemIcon": "",
    "ItemQuality": 0,
    "ItemType": 0,
    "ItemDes": "",
    "BagSlotType": 2,
    "AutoUse": false,
    "BatchUseable": false,
    "UseScript": 0,
    "UseArgs": [],
    "AwakeScript": []
  },
  {
    "id": 10009,
    "isVaild": 0,
    "ItemName": "祝福1",
    "ItemIcon": "",
    "ItemQuality": 0,
    "ItemType": 0,
    "ItemDes": "",
    "BagSlotType": 0,
    "AutoUse": false,
    "BatchUseable": false,
    "UseScript": 3,
    "UseArgs": [
      10002
    ],
    "AwakeScript": []
  },
  {
    "id": 10010,
    "isVaild": 0,
    "ItemName": "称号1",
    "ItemIcon": "",
    "ItemQuality": 0,
    "ItemType": 0,
    "ItemDes": "",
    "BagSlotType": 2,
    "AutoUse": false,
    "BatchUseable": false,
    "UseScript": 0,
    "UseArgs": [],
    "AwakeScript": [
      {
        "ScriptName": 2,
        "ScriptValue": [
          10001
        ]
      }
    ]
  }
]